{
"type": "FeatureCollection",
"name": "addresses",
"crs": { "type": "name", "properties": { "name": "urn:ogc:def:crs:OGC:1.3:CRS84" } },
"features": [
{ "type": "Feature", "properties": { "osm_id": 2384686638, "addr:housenumber": "7060", "addr:street": "Aviation Boulevard" }, "geometry": { "type": "Point", "coordinates": [ -76.652405, 39.18845 ] } },
{ "type": "Feature", "properties": { "osm_id": 2384681075, "addr:housenumber": "7068", "addr:street": null }, "geometry": { "type": "Point", "coordinates": [ -76.65281, 39.189003 ] } }
]
}
